boards/kc705/rtl/setup.v
`define MAGIC_CODE      40'hcc00cc00cc

//`define ENABE_XGMII2
//`define ENABE_XGMII3

boards/kc705/rtl/measure.v
`timescale 1ns / 1ps
//`define DEBUG

module measure (
  input         sys_rst,
  input         sys_clk,

  // XGMII interfaces for 4 MACs
  output [63:0] xgmii_0_txd,
  output [7:0]  xgmii_0_txc,
  input  [63:0] xgmii_0_rxd,
  input  [7:0]  xgmii_0_rxc,

  output [63:0] xgmii_1_txd,
  output [7:0]  xgmii_1_txc,
  input  [63:0] xgmii_1_rxd,
  input  [7:0]  xgmii_1_rxc,

  output [63:0] xgmii_2_txd,
  output [7:0]  xgmii_2_txc,
  input  [63:0] xgmii_2_rxd,
  input  [7:0]  xgmii_2_rxc,

  output [63:0] xgmii_3_txd,
  output [7:0]  xgmii_3_txc,
  input  [63:0] xgmii_3_rxd,
  input  [7:0]  xgmii_3_rxc,

  // PCI user registers
  input         tx0_enable,
  input         tx0_ipv6,
  input         tx0_fullroute,
  input         tx0_req_arp,
  input [15:0]  tx0_frame_len,
  input [31:0]  tx0_inter_frame_gap,
  input [31:0]  tx0_ipv4_srcip,
  input [47:0]  tx0_src_mac,
  input [31:0]  tx0_ipv4_gwip,
  input [127:0]  tx0_ipv6_srcip,
  input [127:0]  tx0_ipv6_dstip,
  output reg [47:0] tx0_dst_mac,
  input [31:0]  tx0_ipv4_dstip,
  output reg [31:0] tx0_pps,
  output reg [31:0] tx0_throughput,
  output [31:0] tx0_ipv4_ip,

  output [31:0] rx1_pps,
  output [31:0] rx1_throughput,
  output [23:0] rx1_latency,
  output [31:0] rx1_ipv4_ip,

  output [31:0] rx2_pps,
  output [31:0] rx2_throughput,
  output [23:0] rx2_latency,
  output [31:0] rx2_ipv4_ip,

  output [31:0] rx3_pps,
  output [31:0] rx3_throughput,
  output [23:0] rx3_latency,
  output [31:0] rx3_ipv4_ip,

  output reg [31:0] global_counter,
  output [31:0] count_2976_latency
);

//-----------------------------------
// One second clock
//-----------------------------------
reg sec_oneshot;
reg [26:0] sec_counter;
always @(posedge sys_clk) begin
  if (sys_rst) begin
    sec_counter <= 27'd156250000;
    sec_oneshot <= 1'b0;
  end else begin
    if (sec_counter == 27'd0) begin
      sec_counter <= 27'd156250000;
      sec_oneshot <= 1'b1;
    end else begin
      sec_counter <= sec_counter - 27'd1;
      sec_oneshot <= 1'b0;
    end
  end
end

//-----------------------------------
// Transmitte logic
//-----------------------------------
reg [15:0] tx_count = 16'h0;
reg [7:0] tx_data;
reg tx_en = 1'b0;

//-----------------------------------
// CRC
//-----------------------------------
assign crc_init = (tx_count ==  16'h08);
wire [31:0] crc_out;
reg crc_rd;
assign crc_data_en = ~crc_rd;
//crc_gen crc_inst (
//  .Reset(sys_rst),
//  .Clk(sys_clk),
//  .Init(crc_init),
//  .Frame_data(tx_data),
//  .Data_en(crc_data_en),
//  .CRC_rd(crc_rd),
//  .CRC_end(),
//  .CRC_out(crc_out)
//); 

//-----------------------------------
// Global counter
//-----------------------------------
always @(posedge sys_clk) begin
  if (sys_rst) begin
    global_counter <= 32'h0;
  end else begin
    global_counter <= global_counter + 32'h1;
  end
end


reg [31:0] tx_counter;
reg [63:0] txd;
reg [7:0] txc;
always @(posedge sys_clk) begin
        if ( sys_rst ) begin
                tx_counter <= 32'h0;
                txd <= 64'h0707070707070707;
                txc <= 8'hff;
        end else begin
                tx_counter <= tx_counter + 32'h8;
                case (tx_counter[15:0] )
                        16'h00: {txc, txd} <= {8'h01, 64'hd5_55_55_55_55_55_55_fb};
                        16'h08: {txc, txd} <= {8'h00, 64'hde_a0_00_d6_7b_1d_25_11};
                        16'h10: {txc, txd} <= {8'h00, 64'h00_00_45_00_08_e8_07_1c};
                        16'h18: {txc, txd} <= {8'h00, 64'h44_01_40_00_00_99_f8_54};
                        16'h20: {txc, txd} <= {8'h00, 64'h16_00_0a_69_15_00_0a_9d};
                        16'h28: {txc, txd} <= {8'h00, 64'h00_07_b8_45_d5_00_08_64};
                        16'h30: {txc, txd} <= {8'h00, 64'hab_05_00_06_84_ac_4f_07};
                        16'h38: {txc, txd} <= {8'h00, 64'h0e_0d_0c_0b_0a_09_08_f0};
                        16'h40: {txc, txd} <= {8'h00, 64'h16_15_14_13_12_11_10_0f};
                        16'h48: {txc, txd} <= {8'h00, 64'h1e_1d_1c_1b_1a_19_18_17};
                        16'h50: {txc, txd} <= {8'h00, 64'h26_25_24_23_22_21_20_1f};
                        16'h58: {txc, txd} <= {8'h00, 64'h2e_2d_2c_2b_2a_29_28_27};
                        16'h60: {txc, txd} <= {8'h00, 64'h36_35_34_33_32_31_30_2f};
                        16'h68: {txc, txd} <= {8'he0, 64'h07_07_fd_ba_fc_4f_47_37};
                        default: begin
                                {txc, txd} <= {8'hff, 64'h07_07_07_07_07_07_07_07};
                        end
                endcase
        end
end

assign xgmii_0_txd = txd;
assign xgmii_0_txc = txc;
assign xgmii_1_txd = txd;
assign xgmii_1_txc = txc;

endmodule

boards/kc705/test/tb_system.v
`timescale 1ps / 1ps
`define SIMULATION
//`include "../rtl/setup.v"
module tb_system();

/* 125MHz system clock */
reg         sys_rst;
reg         sys_clk;	// clk156
initial sys_clk = 1'b0;
always #8 sys_clk = ~sys_clk;

// XGMII interfaces for 4 MACs
wire [63:0] xgmii_0_txd;
wire [7:0]  xgmii_0_txc;
reg  [63:0] xgmii_0_rxd;
reg  [7:0]  xgmii_0_rxc;

wire [63:0] xgmii_1_txd;
wire [7:0]  xgmii_1_txc;
reg  [63:0] xgmii_1_rxd;
reg  [7:0]  xgmii_1_rxc;

wire [63:0] xgmii_2_txd;
wire [7:0]  xgmii_2_txc;
reg  [63:0] xgmii_2_rxd;
reg  [7:0]  xgmii_2_rxc;

wire [63:0] xgmii_3_txd;
wire [7:0]  xgmii_3_txc;
wire [63:0] xgmii_3_rxd;
wire [7:0]  xgmii_3_rxc;

// LED and Switches
reg [7:0] dipsw;
wire [7:0] led;
wire [13:0] segled;
reg btn;

measure measure_inst (
         .sys_rst   (sys_rst),
         .sys_clk   (sys_clk),

  // XGMII interfaces for 4 MACs
	.xgmii_0_txd(xgmii_0_txd),
	.xgmii_0_txc(xgmii_0_txc),
	.xgmii_0_rxd(xgmii_0_rxd),
	.xgmii_0_rxc(xgmii_0_rxc),

	.xgmii_1_txd(xgmii_1_txd),
	.xgmii_1_txc(xgmii_1_txc),
	.xgmii_1_rxd(xgmii_1_rxd),
	.xgmii_1_rxc(xgmii_1_rxc),

	.xgmii_2_txd(xgmii_2_txd),
	.xgmii_2_txc(xgmii_2_txc),
	.xgmii_2_rxd(xgmii_2_rxd),
	.xgmii_2_rxc(xgmii_2_rxc),

	.xgmii_3_txd(xgmii_3_txd),
	.xgmii_3_txc(xgmii_3_txc),
	.xgmii_3_rxd(xgmii_3_rxd),
	.xgmii_3_rxc(xgmii_3_rxc)
);

task waitclock;
begin
	@(posedge sys_clk);
	#1;
end
endtask

/*
always @(posedge Wclk) begin
	if (WriteEn_in == 1'b1)
		$display("Data_in: %x", Data_in);
end
*/

reg [23:0] tlp_rom [0:4095];
reg [11:0] phy_rom [0:4095];
reg [11:0] tlp_counter, phy_counter;
wire [23:0] tlp_cur;
wire [23:0] phy_cur;
assign tlp_cur = tlp_rom[ tlp_counter ];
assign phy_cur = phy_rom[ phy_counter ];

always @(posedge sys_clk) begin
//	rx_st   <= tlp_cur[20];
//	rx_end  <= tlp_cur[16];
//	rx_data <= tlp_cur[15:0];
//	tlp_counter <= tlp_counter + 1;
end

always @(posedge sys_clk) begin
//	gmii_rx_dv  <= phy_cur[8];
//	gmii_rxd <= phy_cur[7:0];
//	phy_counter <= phy_counter + 1;
end

initial begin
        $dumpfile("./test.vcd");
	$dumpvars(0, tb_system); 
	$readmemh("./tlp_data.hex", tlp_rom);
	$readmemh("./phy_data.hex", phy_rom);
	/* Reset / Initialize our logic */
	sys_rst = 1'b1;

	waitclock;
	waitclock;

	sys_rst = 1'b0;

	waitclock;

//	#(500*16) mst_req_o = 1'b1;

//	#(8*2) mst_req_o = 1'b0;

	#4000;

	$finish;
end

endmodule

boards/kc705/test/test.vcd
$date
	Wed May 21 21:50:07 2014
$end
$version
	Icarus Verilog
$end
$timescale
	1ps
$end
$scope module tb_system $end
$var wire 24 ! phy_cur [23:0] $end
$var wire 24 " tlp_cur [23:0] $end
$var wire 8 # xgmii_0_txc [7:0] $end
$var wire 64 $ xgmii_0_txd [63:0] $end
$var wire 8 % xgmii_1_txc [7:0] $end
$var wire 64 & xgmii_1_txd [63:0] $end
$var wire 8 ' xgmii_2_txc [7:0] $end
$var wire 64 ( xgmii_2_txd [63:0] $end
$var wire 8 ) xgmii_3_rxc [7:0] $end
$var wire 64 * xgmii_3_rxd [63:0] $end
$var wire 8 + xgmii_3_txc [7:0] $end
$var wire 64 , xgmii_3_txd [63:0] $end
$var reg 12 - phy_counter [11:0] $end
$var reg 1 . sys_clk $end
$var reg 1 / sys_rst $end
$var reg 12 0 tlp_counter [11:0] $end
$var reg 8 1 xgmii_0_rxc [7:0] $end
$var reg 64 2 xgmii_0_rxd [63:0] $end
$var reg 8 3 xgmii_1_rxc [7:0] $end
$var reg 64 4 xgmii_1_rxd [63:0] $end
$var reg 8 5 xgmii_2_rxc [7:0] $end
$var reg 64 6 xgmii_2_rxd [63:0] $end
$scope module measure_inst $end
$var wire 32 7 count_2976_latency [31:0] $end
$var wire 1 8 crc_data_en $end
$var wire 1 9 crc_init $end
$var wire 32 : rx1_ipv4_ip [31:0] $end
$var wire 24 ; rx1_latency [23:0] $end
$var wire 32 < rx1_pps [31:0] $end
$var wire 32 = rx1_throughput [31:0] $end
$var wire 32 > rx2_ipv4_ip [31:0] $end
$var wire 24 ? rx2_latency [23:0] $end
$var wire 32 @ rx2_pps [31:0] $end
$var wire 32 A rx2_throughput [31:0] $end
$var wire 32 B rx3_ipv4_ip [31:0] $end
$var wire 24 C rx3_latency [23:0] $end
$var wire 32 D rx3_pps [31:0] $end
$var wire 32 E rx3_throughput [31:0] $end
$var wire 1 F sys_clk $end
$var wire 1 G sys_rst $end
$var wire 1 H tx0_enable $end
$var wire 16 I tx0_frame_len [15:0] $end
$var wire 1 J tx0_fullroute $end
$var wire 32 K tx0_inter_frame_gap [31:0] $end
$var wire 32 L tx0_ipv4_dstip [31:0] $end
$var wire 32 M tx0_ipv4_gwip [31:0] $end
$var wire 32 N tx0_ipv4_ip [31:0] $end
$var wire 32 O tx0_ipv4_srcip [31:0] $end
$var wire 1 P tx0_ipv6 $end
$var wire 128 Q tx0_ipv6_dstip [127:0] $end
$var wire 128 R tx0_ipv6_srcip [127:0] $end
$var wire 1 S tx0_req_arp $end
$var wire 48 T tx0_src_mac [47:0] $end
$var wire 8 U xgmii_0_rxc [7:0] $end
$var wire 64 V xgmii_0_rxd [63:0] $end
$var wire 8 W xgmii_0_txc [7:0] $end
$var wire 64 X xgmii_0_txd [63:0] $end
$var wire 8 Y xgmii_1_rxc [7:0] $end
$var wire 64 Z xgmii_1_rxd [63:0] $end
$var wire 8 [ xgmii_1_txc [7:0] $end
$var wire 64 \ xgmii_1_txd [63:0] $end
$var wire 8 ] xgmii_2_rxc [7:0] $end
$var wire 64 ^ xgmii_2_rxd [63:0] $end
$var wire 8 _ xgmii_2_txc [7:0] $end
$var wire 64 ` xgmii_2_txd [63:0] $end
$var wire 8 a xgmii_3_rxc [7:0] $end
$var wire 64 b xgmii_3_rxd [63:0] $end
$var wire 8 c xgmii_3_txc [7:0] $end
$var wire 64 d xgmii_3_txd [63:0] $end
$var reg 1 e crc_rd $end
$var reg 32 f global_counter [31:0] $end
$var reg 27 g sec_counter [26:0] $end
$var reg 1 h sec_oneshot $end
$var reg 48 i tx0_dst_mac [47:0] $end
$var reg 32 j tx0_pps [31:0] $end
$var reg 32 k tx0_throughput [31:0] $end
$var reg 16 l tx_count [15:0] $end
$var reg 32 m tx_counter [31:0] $end
$var reg 1 n tx_en $end
$var reg 8 o txc [7:0] $end
$var reg 64 p txd [63:0] $end
$upscope $end
$scope task waitclock $end
$upscope $end
$upscope $end
$enddefinitions $end
#0
$dumpvars
bx p
bx o
0n
bx m
b0 l
bx k
bx j
bx i
xh
bx g
bx f
xe
bz d
bz c
bz b
bz a
bz `
bz _
bx ^
bx ]
bx \
bx [
bx Z
bx Y
bx X
bx W
bx V
bx U
bz T
zS
bz R
bz Q
zP
bz O
bz N
bz M
bz L
bz K
zJ
bz I
zH
1G
0F
bz E
bz D
bz C
bz B
bz A
bz @
bz ?
bz >
bz =
bz <
bz ;
bz :
09
x8
bz 7
bx 6
bx 5
bx 4
bx 3
bx 2
bx 1
bx 0
1/
0.
bx -
bz ,
bz +
bz *
bz )
bz (
bz '
bx &
bx %
bx $
bx #
bx "
b0xxxxxxxxxxxx !
$end
#8
0h
b1010100000010111110010000 g
b0 f
b11111111 o
b11111111 %
b11111111 [
b11111111 #
b11111111 W
b11100000111000001110000011100000111000001110000011100000111 p
b11100000111000001110000011100000111000001110000011100000111 &
b11100000111000001110000011100000111000001110000011100000111 \
b11100000111000001110000011100000111000001110000011100000111 $
b11100000111000001110000011100000111000001110000011100000111 X
b0 m
1.
1F
#16
0.
0F
#24
1.
1F
#25
0/
0G
#32
0.
0F
#40
b1010100000010111110001111 g
b1 f
b1 o
b1 %
b1 [
b1 #
b1 W
b1101010101010101010101010101010101010101010101010101010111111011 p
b1101010101010101010101010101010101010101010101010101010111111011 &
b1101010101010101010101010101010101010101010101010101010111111011 \
b1101010101010101010101010101010101010101010101010101010111111011 $
b1101010101010101010101010101010101010101010101010101010111111011 X
b1000 m
1.
1F
#48
0.
0F
#56
b0 o
b0 %
b0 [
b0 #
b0 W
b1101111010100000000000001101011001111011000111010010010100010001 p
b1101111010100000000000001101011001111011000111010010010100010001 &
b1101111010100000000000001101011001111011000111010010010100010001 \
b1101111010100000000000001101011001111011000111010010010100010001 $
b1101111010100000000000001101011001111011000111010010010100010001 X
b10000 m
b10 f
b1010100000010111110001110 g
1.
1F
#64
0.
0F
#72
b1010100000010111110001101 g
b11 f
b10001010000000000001000111010000000011100011100 p
b10001010000000000001000111010000000011100011100 &
b10001010000000000001000111010000000011100011100 \
b10001010000000000001000111010000000011100011100 $
b10001010000000000001000111010000000011100011100 X
b11000 m
1.
1F
#80
0.
0F
#88
b100010000000001010000000000000000000000100110011111100001010100 p
b100010000000001010000000000000000000000100110011111100001010100 &
b100010000000001010000000000000000000000100110011111100001010100 \
b100010000000001010000000000000000000000100110011111100001010100 $
b100010000000001010000000000000000000000100110011111100001010100 X
b100000 m
b100 f
b1010100000010111110001100 g
1.
1F
#96
0.
0F
#104
b1010100000010111110001011 g
b101 f
b1011000000000000010100110100100010101000000000000101010011101 p
b1011000000000000010100110100100010101000000000000101010011101 &
b1011000000000000010100110100100010101000000000000101010011101 \
b1011000000000000010100110100100010101000000000000101010011101 $
b1011000000000000010100110100100010101000000000000101010011101 X
b101000 m
1.
1F
#112
0.
0F
#120
b111101110000100010111010101000000000000100001100100 p
b111101110000100010111010101000000000000100001100100 &
b111101110000100010111010101000000000000100001100100 \
b111101110000100010111010101000000000000100001100100 $
b111101110000100010111010101000000000000100001100100 X
b110000 m
b110 f
b1010100000010111110001010 g
1.
1F
#128
0.
0F
#136
b1010100000010111110001001 g
b111 f
b1010101100000101000000000000011010000100101011000100111100000111 p
b1010101100000101000000000000011010000100101011000100111100000111 &
b1010101100000101000000000000011010000100101011000100111100000111 \
b1010101100000101000000000000011010000100101011000100111100000111 $
b1010101100000101000000000000011010000100101011000100111100000111 X
b111000 m
1.
1F
#144
0.
0F
#152
b111000001101000011000000101100001010000010010000100011110000 p
b111000001101000011000000101100001010000010010000100011110000 &
b111000001101000011000000101100001010000010010000100011110000 \
b111000001101000011000000101100001010000010010000100011110000 $
b111000001101000011000000101100001010000010010000100011110000 X
b1000000 m
b1000 f
b1010100000010111110001000 g
1.
1F
#160
0.
0F
#168
b1010100000010111110000111 g
b1001 f
b1011000010101000101000001001100010010000100010001000000001111 p
b1011000010101000101000001001100010010000100010001000000001111 &
b1011000010101000101000001001100010010000100010001000000001111 \
b1011000010101000101000001001100010010000100010001000000001111 $
b1011000010101000101000001001100010010000100010001000000001111 X
b1001000 m
1.
1F
#176
0.
0F
#184
b1111000011101000111000001101100011010000110010001100000010111 p
b1111000011101000111000001101100011010000110010001100000010111 &
b1111000011101000111000001101100011010000110010001100000010111 \
b1111000011101000111000001101100011010000110010001100000010111 $
b1111000011101000111000001101100011010000110010001100000010111 X
b1010000 m
b1010 f
b1010100000010111110000110 g
1.
1F
#192
0.
0F
#200
b1010100000010111110000101 g
b1011 f
b10011000100101001001000010001100100010001000010010000000011111 p
b10011000100101001001000010001100100010001000010010000000011111 &
b10011000100101001001000010001100100010001000010010000000011111 \
b10011000100101001001000010001100100010001000010010000000011111 $
b10011000100101001001000010001100100010001000010010000000011111 X
b1011000 m
1.
1F
#208
0.
0F
#216
b10111000101101001011000010101100101010001010010010100000100111 p
b10111000101101001011000010101100101010001010010010100000100111 &
b10111000101101001011000010101100101010001010010010100000100111 \
b10111000101101001011000010101100101010001010010010100000100111 $
b10111000101101001011000010101100101010001010010010100000100111 X
b1100000 m
b1100 f
b1010100000010111110000100 g
1.
1F
#224
0.
0F
#232
b1010100000010111110000011 g
b1101 f
b11011000110101001101000011001100110010001100010011000000101111 p
b11011000110101001101000011001100110010001100010011000000101111 &
b11011000110101001101000011001100110010001100010011000000101111 \
b11011000110101001101000011001100110010001100010011000000101111 $
b11011000110101001101000011001100110010001100010011000000101111 X
b1101000 m
1.
1F
#240
0.
0F
#248
b11100000 o
b11100000 %
b11100000 [
b11100000 #
b11100000 W
b11100000111111111011011101011111100010011110100011100110111 p
b11100000111111111011011101011111100010011110100011100110111 &
b11100000111111111011011101011111100010011110100011100110111 \
b11100000111111111011011101011111100010011110100011100110111 $
b11100000111111111011011101011111100010011110100011100110111 X
b1110000 m
b1110 f
b1010100000010111110000010 g
1.
1F
#256
0.
0F
#264
b1010100000010111110000001 g
b1111 f
b11111111 o
b11111111 %
b11111111 [
b11111111 #
b11111111 W
b11100000111000001110000011100000111000001110000011100000111 p
b11100000111000001110000011100000111000001110000011100000111 &
b11100000111000001110000011100000111000001110000011100000111 \
b11100000111000001110000011100000111000001110000011100000111 $
b11100000111000001110000011100000111000001110000011100000111 X
b1111000 m
1.
1F
#272
0.
0F
#280
b10000000 m
b10000 f
b1010100000010111110000000 g
1.
1F
#288
0.
0F
#296
b1010100000010111101111111 g
b10001 f
b10001000 m
1.
1F
#304
0.
0F
#312
b10010000 m
b10010 f
b1010100000010111101111110 g
1.
1F
#320
0.
0F
#328
b1010100000010111101111101 g
b10011 f
b10011000 m
1.
1F
#336
0.
0F
#344
b10100000 m
b10100 f
b1010100000010111101111100 g
1.
1F
#352
0.
0F
#360
b1010100000010111101111011 g
b10101 f
b10101000 m
1.
1F
#368
0.
0F
#376
b10110000 m
b10110 f
b1010100000010111101111010 g
1.
1F
#384
0.
0F
#392
b1010100000010111101111001 g
b10111 f
b10111000 m
1.
1F
#400
0.
0F
#408
b11000000 m
b11000 f
b1010100000010111101111000 g
1.
1F
#416
0.
0F
#424
b1010100000010111101110111 g
b11001 f
b11001000 m
1.
1F
#432
0.
0F
#440
b11010000 m
b11010 f
b1010100000010111101110110 g
1.
1F
#448
0.
0F
#456
b1010100000010111101110101 g
b11011 f
b11011000 m
1.
1F
#464
0.
0F
#472
b11100000 m
b11100 f
b1010100000010111101110100 g
1.
1F
#480
0.
0F
#488
b1010100000010111101110011 g
b11101 f
b11101000 m
1.
1F
#496
0.
0F
#504
b11110000 m
b11110 f
b1010100000010111101110010 g
1.
1F
#512
0.
0F
#520
b1010100000010111101110001 g
b11111 f
b11111000 m
1.
1F
#528
0.
0F
#536
b100000000 m
b100000 f
b1010100000010111101110000 g
1.
1F
#544
0.
0F
#552
b1010100000010111101101111 g
b100001 f
b100001000 m
1.
1F
#560
0.
0F
#568
b100010000 m
b100010 f
b1010100000010111101101110 g
1.
1F
#576
0.
0F
#584
b1010100000010111101101101 g
b100011 f
b100011000 m
1.
1F
#592
0.
0F
#600
b100100000 m
b100100 f
b1010100000010111101101100 g
1.
1F
#608
0.
0F
#616
b1010100000010111101101011 g
b100101 f
b100101000 m
1.
1F
#624
0.
0F
#632
b100110000 m
b100110 f
b1010100000010111101101010 g
1.
1F
#640
0.
0F
#648
b1010100000010111101101001 g
b100111 f
b100111000 m
1.
1F
#656
0.
0F
#664
b101000000 m
b101000 f
b1010100000010111101101000 g
1.
1F
#672
0.
0F
#680
b1010100000010111101100111 g
b101001 f
b101001000 m
1.
1F
#688
0.
0F
#696
b101010000 m
b101010 f
b1010100000010111101100110 g
1.
1F
#704
0.
0F
#712
b1010100000010111101100101 g
b101011 f
b101011000 m
1.
1F
#720
0.
0F
#728
b101100000 m
b101100 f
b1010100000010111101100100 g
1.
1F
#736
0.
0F
#744
b1010100000010111101100011 g
b101101 f
b101101000 m
1.
1F
#752
0.
0F
#760
b101110000 m
b101110 f
b1010100000010111101100010 g
1.
1F
#768
0.
0F
#776
b1010100000010111101100001 g
b101111 f
b101111000 m
1.
1F
#784
0.
0F
#792
b110000000 m
b110000 f
b1010100000010111101100000 g
1.
1F
#800
0.
0F
#808
b1010100000010111101011111 g
b110001 f
b110001000 m
1.
1F
#816
0.
0F
#824
b110010000 m
b110010 f
b1010100000010111101011110 g
1.
1F
#832
0.
0F
#840
b1010100000010111101011101 g
b110011 f
b110011000 m
1.
1F
#848
0.
0F
#856
b110100000 m
b110100 f
b1010100000010111101011100 g
1.
1F
#864
0.
0F
#872
b1010100000010111101011011 g
b110101 f
b110101000 m
1.
1F
#880
0.
0F
#888
b110110000 m
b110110 f
b1010100000010111101011010 g
1.
1F
#896
0.
0F
#904
b1010100000010111101011001 g
b110111 f
b110111000 m
1.
1F
#912
0.
0F
#920
b111000000 m
b111000 f
b1010100000010111101011000 g
1.
1F
#928
0.
0F
#936
b1010100000010111101010111 g
b111001 f
b111001000 m
1.
1F
#944
0.
0F
#952
b111010000 m
b111010 f
b1010100000010111101010110 g
1.
1F
#960
0.
0F
#968
b1010100000010111101010101 g
b111011 f
b111011000 m
1.
1F
#976
0.
0F
#984
b111100000 m
b111100 f
b1010100000010111101010100 g
1.
1F
#992
0.
0F
#1000
b1010100000010111101010011 g
b111101 f
b111101000 m
1.
1F
#1008
0.
0F
#1016
b111110000 m
b111110 f
b1010100000010111101010010 g
1.
1F
#1024
0.
0F
#1032
b1010100000010111101010001 g
b111111 f
b111111000 m
1.
1F
#1040
0.
0F
#1048
b1000000000 m
b1000000 f
b1010100000010111101010000 g
1.
1F
#1056
0.
0F
#1064
b1010100000010111101001111 g
b1000001 f
b1000001000 m
1.
1F
#1072
0.
0F
#1080
b1000010000 m
b1000010 f
b1010100000010111101001110 g
1.
1F
#1088
0.
0F
#1096
b1010100000010111101001101 g
b1000011 f
b1000011000 m
1.
1F
#1104
0.
0F
#1112
b1000100000 m
b1000100 f
b1010100000010111101001100 g
1.
1F
#1120
0.
0F
#1128
b1010100000010111101001011 g
b1000101 f
b1000101000 m
1.
1F
#1136
0.
0F
#1144
b1000110000 m
b1000110 f
b1010100000010111101001010 g
1.
1F
#1152
0.
0F
#1160
b1010100000010111101001001 g
b1000111 f
b1000111000 m
1.
1F
#1168
0.
0F
#1176
b1001000000 m
b1001000 f
b1010100000010111101001000 g
1.
1F
#1184
0.
0F
#1192
b1010100000010111101000111 g
b1001001 f
b1001001000 m
1.
1F
#1200
0.
0F
#1208
b1001010000 m
b1001010 f
b1010100000010111101000110 g
1.
1F
#1216
0.
0F
#1224
b1010100000010111101000101 g
b1001011 f
b1001011000 m
1.
1F
#1232
0.
0F
#1240
b1001100000 m
b1001100 f
b1010100000010111101000100 g
1.
1F
#1248
0.
0F
#1256
b1010100000010111101000011 g
b1001101 f
b1001101000 m
1.
1F
#1264
0.
0F
#1272
b1001110000 m
b1001110 f
b1010100000010111101000010 g
1.
1F
#1280
0.
0F
#1288
b1010100000010111101000001 g
b1001111 f
b1001111000 m
1.
1F
#1296
0.
0F
#1304
b1010000000 m
b1010000 f
b1010100000010111101000000 g
1.
1F
#1312
0.
0F
#1320
b1010100000010111100111111 g
b1010001 f
b1010001000 m
1.
1F
#1328
0.
0F
#1336
b1010010000 m
b1010010 f
b1010100000010111100111110 g
1.
1F
#1344
0.
0F
#1352
b1010100000010111100111101 g
b1010011 f
b1010011000 m
1.
1F
#1360
0.
0F
#1368
b1010100000 m
b1010100 f
b1010100000010111100111100 g
1.
1F
#1376
0.
0F
#1384
b1010100000010111100111011 g
b1010101 f
b1010101000 m
1.
1F
#1392
0.
0F
#1400
b1010110000 m
b1010110 f
b1010100000010111100111010 g
1.
1F
#1408
0.
0F
#1416
b1010100000010111100111001 g
b1010111 f
b1010111000 m
1.
1F
#1424
0.
0F
#1432
b1011000000 m
b1011000 f
b1010100000010111100111000 g
1.
1F
#1440
0.
0F
#1448
b1010100000010111100110111 g
b1011001 f
b1011001000 m
1.
1F
#1456
0.
0F
#1464
b1011010000 m
b1011010 f
b1010100000010111100110110 g
1.
1F
#1472
0.
0F
#1480
b1010100000010111100110101 g
b1011011 f
b1011011000 m
1.
1F
#1488
0.
0F
#1496
b1011100000 m
b1011100 f
b1010100000010111100110100 g
1.
1F
#1504
0.
0F
#1512
b1010100000010111100110011 g
b1011101 f
b1011101000 m
1.
1F
#1520
0.
0F
#1528
b1011110000 m
b1011110 f
b1010100000010111100110010 g
1.
1F
#1536
0.
0F
#1544
b1010100000010111100110001 g
b1011111 f
b1011111000 m
1.
1F
#1552
0.
0F
#1560
b1100000000 m
b1100000 f
b1010100000010111100110000 g
1.
1F
#1568
0.
0F
#1576
b1010100000010111100101111 g
b1100001 f
b1100001000 m
1.
1F
#1584
0.
0F
#1592
b1100010000 m
b1100010 f
b1010100000010111100101110 g
1.
1F
#1600
0.
0F
#1608
b1010100000010111100101101 g
b1100011 f
b1100011000 m
1.
1F
#1616
0.
0F
#1624
b1100100000 m
b1100100 f
b1010100000010111100101100 g
1.
1F
#1632
0.
0F
#1640
b1010100000010111100101011 g
b1100101 f
b1100101000 m
1.
1F
#1648
0.
0F
#1656
b1100110000 m
b1100110 f
b1010100000010111100101010 g
1.
1F
#1664
0.
0F
#1672
b1010100000010111100101001 g
b1100111 f
b1100111000 m
1.
1F
#1680
0.
0F
#1688
b1101000000 m
b1101000 f
b1010100000010111100101000 g
1.
1F
#1696
0.
0F
#1704
b1010100000010111100100111 g
b1101001 f
b1101001000 m
1.
1F
#1712
0.
0F
#1720
b1101010000 m
b1101010 f
b1010100000010111100100110 g
1.
1F
#1728
0.
0F
#1736
b1010100000010111100100101 g
b1101011 f
b1101011000 m
1.
1F
#1744
0.
0F
#1752
b1101100000 m
b1101100 f
b1010100000010111100100100 g
1.
1F
#1760
0.
0F
#1768
b1010100000010111100100011 g
b1101101 f
b1101101000 m
1.
1F
#1776
0.
0F
#1784
b1101110000 m
b1101110 f
b1010100000010111100100010 g
1.
1F
#1792
0.
0F
#1800
b1010100000010111100100001 g
b1101111 f
b1101111000 m
1.
1F
#1808
0.
0F
#1816
b1110000000 m
b1110000 f
b1010100000010111100100000 g
1.
1F
#1824
0.
0F
#1832
b1010100000010111100011111 g
b1110001 f
b1110001000 m
1.
1F
#1840
0.
0F
#1848
b1110010000 m
b1110010 f
b1010100000010111100011110 g
1.
1F
#1856
0.
0F
#1864
b1010100000010111100011101 g
b1110011 f
b1110011000 m
1.
1F
#1872
0.
0F
#1880
b1110100000 m
b1110100 f
b1010100000010111100011100 g
1.
1F
#1888
0.
0F
#1896
b1010100000010111100011011 g
b1110101 f
b1110101000 m
1.
1F
#1904
0.
0F
#1912
b1110110000 m
b1110110 f
b1010100000010111100011010 g
1.
1F
#1920
0.
0F
#1928
b1010100000010111100011001 g
b1110111 f
b1110111000 m
1.
1F
#1936
0.
0F
#1944
b1111000000 m
b1111000 f
b1010100000010111100011000 g
1.
1F
#1952
0.
0F
#1960
b1010100000010111100010111 g
b1111001 f
b1111001000 m
1.
1F
#1968
0.
0F
#1976
b1111010000 m
b1111010 f
b1010100000010111100010110 g
1.
1F
#1984
0.
0F
#1992
b1010100000010111100010101 g
b1111011 f
b1111011000 m
1.
1F
#2000
0.
0F
#2008
b1111100000 m
b1111100 f
b1010100000010111100010100 g
1.
1F
#2016
0.
0F
#2024
b1010100000010111100010011 g
b1111101 f
b1111101000 m
1.
1F
#2032
0.
0F
#2040
b1111110000 m
b1111110 f
b1010100000010111100010010 g
1.
1F
#2048
0.
0F
#2056
b1010100000010111100010001 g
b1111111 f
b1111111000 m
1.
1F
#2064
0.
0F
#2072
b10000000000 m
b10000000 f
b1010100000010111100010000 g
1.
1F
#2080
0.
0F
#2088
b1010100000010111100001111 g
b10000001 f
b10000001000 m
1.
1F
#2096
0.
0F
#2104
b10000010000 m
b10000010 f
b1010100000010111100001110 g
1.
1F
#2112
0.
0F
#2120
b1010100000010111100001101 g
b10000011 f
b10000011000 m
1.
1F
#2128
0.
0F
#2136
b10000100000 m
b10000100 f
b1010100000010111100001100 g
1.
1F
#2144
0.
0F
#2152
b1010100000010111100001011 g
b10000101 f
b10000101000 m
1.
1F
#2160
0.
0F
#2168
b10000110000 m
b10000110 f
b1010100000010111100001010 g
1.
1F
#2176
0.
0F
#2184
b1010100000010111100001001 g
b10000111 f
b10000111000 m
1.
1F
#2192
0.
0F
#2200
b10001000000 m
b10001000 f
b1010100000010111100001000 g
1.
1F
#2208
0.
0F
#2216
b1010100000010111100000111 g
b10001001 f
b10001001000 m
1.
1F
#2224
0.
0F
#2232
b10001010000 m
b10001010 f
b1010100000010111100000110 g
1.
1F
#2240
0.
0F
